{
 	"_AXIS_ENTRY_FILE":"obs4MIPs_coordinate.json",
	"_FORMULA_VAR_FILE":"obs4MIPs_formula_terms.json",
    	"_controlled_vocabulary_file":"obs4MIPs_CV.json",
    	"_history_template":"%s; CMOR rewrote data to be consistent with <activity_id>, and <Conventions> standards",
    	"activity_id":"obs4MIPs",
        "data_specs_version":"ODS-2.5",

    	"contact":"sha2128@columbia.edu, pg2328@columbia.edu",
	"dataset_contributor":"Dora Hegedus and Min Xu are acknowledged assisting in the preparation of this dataset for obs4MIPs",
    	"doi":"",
	"frequency":"mon",
	"grid":"1 x 1 degree latitude x longitude",
    	"grid_label":"gn",
    	"license":"Creative Commons Attribution- 4.0 International (CC BY 4.0) License (https://creativecommons.org/licenses/).",
    	"institution_id":"ColumbiaU",
	"institution":"Columbia University, NY, USA",
    	"nominal_resolution":"100 km",
    	"product":"observations",
	"realm":"atmos",
	"region":"global",

	"references":"https://bg.copernicus.org/articles/14/4101/2017/",
	"source_id":"WECANN-1-0",
	"source":"Solar Induced Fluorescence (SIF), Air Temperature, Precipitation, Net Radiation, Soil Moisture, and Snow Water Equivalent",
	"source_type":"satellite_merged",
	"source_version_number":"1-0",
	"source_data_url": "https://avdc.gsfc.nasa.gov/pub/data/project/WECANN/",
	"title": "Water, Energy, and Carbon with Artificial Neural Networks (WECANN)",
	"variant_info":"ILAMB-ready data made obs4MIPs-compliant (ODS2.5)",
	"variant_label":"ILAMB-REF",
	"calendar":"standard",
        "mip_era":"CMIP6",
	
	"outpath":"/p/user_pub/PCMDIobs/",
	"output_file_template":"<variable_id><frequency><source_id><variant_label><grid_label>",
	"output_path_template":"<activity_id>/<institution_id>/<source_id>/<frequency>/<variable_id>/<grid_label>/<version>",
        "mip_era":"CMIP6",
}
