{
    "Header":{
        "Conventions":"CF-1.6 CMIP-6.0",
        "approx_interval":"",
        "cmor_version":"3.2",
        "data_specs_version":"01.00.00",
        "frequency":"fx",
        "generic_levels":"",
        "mip_era":"CMIP6",
        "missing_value":"1e20",
        "product":"output",
        "realm":"ocean",
        "table_date":"13 January 2017",
        "table_id":"Table Ofx"
    },
    "variable_entry":{
        "areacello":{
            "cell_measures":"",
            "cell_methods":"",
            "comment":"Horizontal area of ocean grid cells",
            "dimensions":"longitude latitude",
            "long_name":"Ocean Grid-Cell Area",
            "modeling_realm":"ocean",
            "ok_max_mean_abs":"",
            "ok_min_mean_abs":"",
            "out_name":"areacello",
            "positive":"",
            "standard_name":"cell_area",
            "type":"real",
            "units":"m2",
            "valid_max":"",
            "valid_min":""
        },
        "basin":{
            "cell_measures":"area: areacello",
            "cell_methods":"area: point",
            "comment":"",
            "dimensions":"longitude latitude",
            "flag_meanings":"global_land southern_ocean atlantic_ocean pacific_ocean arctic_ocean indian_ocean mediterranean_sea black_sea hudson_bay baltic_sea red_sea",
            "flag_values":"0 1 2 3 4 5 6 7 8 9 10",
            "long_name":"Region Selection Index",
            "modeling_realm":"ocean",
            "ok_max_mean_abs":"",
            "ok_min_mean_abs":"",
            "out_name":"basin",
            "positive":"",
            "standard_name":"region",
            "type":"integer",
            "units":"1.0",
            "valid_max":"",
            "valid_min":""
        },
        "cpocean":{
            "cell_measures":"",
            "cell_methods":"",
            "comment":"A global constant used to convert between temperature flux and heat flux, and to compute heat content of sea water.",
            "dimensions":"",
            "long_name":"Sea water specific heat capacity",
            "modeling_realm":"ocean",
            "ok_max_mean_abs":"",
            "ok_min_mean_abs":"",
            "out_name":"cpocean",
            "positive":"",
            "standard_name":"specific_heat_capacity_of_seawater",
            "type":"real",
            "units":"J kg-1 K-1",
            "valid_max":"",
            "valid_min":""
        },
        "deptho":{
            "cell_measures":"area: areacello",
            "cell_methods":"area: mean",
            "comment":"Ocean bathymetry.   Reported here is the sea floor depth for present day relative to z=0 geoid. Reported as missing for land grid cells.",
            "dimensions":"longitude latitude",
            "long_name":"Sea Floor Depth Below Geoid",
            "modeling_realm":"ocean",
            "ok_max_mean_abs":"",
            "ok_min_mean_abs":"",
            "out_name":"deptho",
            "positive":"",
            "standard_name":"sea_floor_depth_below_geoid",
            "type":"real",
            "units":"m",
            "valid_max":"",
            "valid_min":""
        },
        "masscello":{
            "cell_measures":"",
            "cell_methods":"",
            "comment":"Tracer grid-cell mass per unit area used for computing tracer budgets. For Boussinesq models with static ocean grid cell thickness, masscello = rhozero*thickcello, where thickcello is static cell thickness and rhozero is constant Boussinesq reference density. More generally, masscello is time dependent and reported as part of Omon.",
            "dimensions":"longitude latitude olevel",
            "long_name":"Ocean Grid-Cell Mass per area",
            "modeling_realm":"ocean",
            "ok_max_mean_abs":"",
            "ok_min_mean_abs":"",
            "out_name":"masscello",
            "positive":"",
            "standard_name":"sea_water_mass_per_unit_area",
            "type":"real",
            "units":"kg m-2",
            "valid_max":"",
            "valid_min":""
        },
        "rhozero":{
            "cell_measures":"",
            "cell_methods":"",
            "comment":"Relevant only for Boussinesq ocean models",
            "dimensions":"",
            "long_name":"Boussinesq reference density",
            "modeling_realm":"ocean",
            "ok_max_mean_abs":"",
            "ok_min_mean_abs":"",
            "out_name":"rhozero",
            "positive":"",
            "standard_name":"reference_sea_water_density_for_Boussinesq_approximation",
            "type":"real",
            "units":"kg m-3",
            "valid_max":"",
            "valid_min":""
        }
    }
}